woo_sy/__init__.py
woo_sy/etsy.py
woo_sy/listing.py
woo_sy/woo_commerce.py
woo_sy/wordpress.py
woo_sy-0.1.2.dist-info/LICENSE.txt
woo_sy-0.1.2.dist-info/WHEEL
woo_sy-0.1.2.dist-info/METADATA
woo_sy-0.1.2.dist-info/RECORD
