Metadata-Version: 2.1
Name: woo-sy
Version: 0.1.2
Summary: WooCommerce + Etsy = woo-sy | A tool for syncing listings between the two
Home-page: UNKNOWN
License: Apache-2.0
Author: Alexander VanTol
Author-email: alexander.m.vantol@gmail.com
Requires-Python: >=3,<4
Classifier: License :: OSI Approved :: Apache Software License
Classifier: Programming Language :: Python :: 3
Classifier: Programming Language :: Python :: 3.4
Classifier: Programming Language :: Python :: 3.5
Classifier: Programming Language :: Python :: 3.6
Classifier: Programming Language :: Python :: 3.7
Requires-Dist: etsy_py (>=1.0,<2.0)
Requires-Dist: python-wordpress-xmlrpc (>=2.3,<3.0)
Requires-Dist: woocommerce (>=1.2,<2.0)
